ramp/__init__.py
ramp/_version.py
ramp/cli.py
ramp/ramp_convert_old_input_files.py
ramp/ramp_run.py
ramp/test_probability.py
ramp/yearly_profile_hourly_resolution.csv
ramp/yearly_profile_min_resolution.csv
ramp/core/__init__.py
ramp/core/constants.py
ramp/core/core.py
ramp/core/utils.py
ramp/errors_logs/__init__.py
ramp/errors_logs/errors.py
ramp/example/T_gw.csv
ramp/example/__init__.py
ramp/example/daily_T.csv
ramp/example/examples.py
ramp/example/here_results.csv
ramp/example/input_file_1.py
ramp/example/input_file_1.xlsx
ramp/example/input_file_2.py
ramp/example/input_file_2.xlsx
ramp/example/input_file_3.py
ramp/example/input_file_3.xlsx
ramp/example/shower_P.csv
ramp/example/shower_P_small.csv
ramp/post_process/__init__.py
ramp/post_process/post_process.py
ramp/results/__init__.py
ramp/results/output_file_1.csv
ramp/results/output_file_2.csv
ramp/results/output_file_3.csv
ramp/results/output_file_4.csv
ramp/results/output_file_example_excel_usecase_xlsx.csv
ramp/results/output_file_input_file_1_xlsx.csv
ramp/results/output_file_input_file_2_xlsx.csv
ramp/results/output_file_input_file_3_xlsx.csv
ramp/results/output_file_input_file_6_xlsx.csv
ramp/results/output_file_ramp_example_input_file_1.csv
ramp/results/output_file_review_uc_xlsx.csv
ramp/test/__init__.py
ramp/test/output_file_1.csv
ramp/test/output_file_2.csv
ramp/test/output_file_3.csv
ramp/test/test_run.py
tests/__init__.py
tests/__test_appliance.py
tests/__test_core.py
tests/__test_duty_cycle.py
tests/__test_func_cycle.py
tests/__test_year_behavior.py
tests/requirements.txt
tests/test_calc_peak_time_range.py
tests/test_cli.py
tests/test_duty_cycle_repetition.py
tests/test_func_time_zero.py
tests/test_input_file_conversion.py
tests/test_notebooks.py
tests/test_object_comparison.py
tests/test_object_creation.py
tests/test_rand_total_time_of_use.py
tests/test_switch_on.py
tests/utils.py
tests/yearly_profile_hourly_resolution.csv
tests/yearly_profile_min_resolution.csv
rampdemand-0.5.2.dist-info/AUTHORS
rampdemand-0.5.2.dist-info/LICENSE
rampdemand-0.5.2.dist-info/METADATA
rampdemand-0.5.2.dist-info/WHEEL
rampdemand-0.5.2.dist-info/entry_points.txt
rampdemand-0.5.2.dist-info/top_level.txt
rampdemand-0.5.2.dist-info/RECORD
