Metadata-Version: 2.1
Name: rampdemand
Version: 0.5.2
Summary: An open-source python package for building bottom-up stochastic model for generating multi-energy load profiles
Home-page: https://github.com/RAMP-project/RAMP
Author-email: f.lombardi@tudelft.nl
License: European Union Public License 1.2
Requires-Python: <3.12
License-File: LICENSE
License-File: AUTHORS
Requires-Dist: pandas >=1.3.3
Requires-Dist: numpy >=1.21.2
Requires-Dist: xlsxwriter >=1.3.7
Requires-Dist: matplotlib >=3.3.4
Requires-Dist: openpyxl >=3.0.6
Requires-Dist: tqdm
Requires-Dist: plotly
Requires-Dist: multiprocess
